nodeconductor_openstack/__init__.py
nodeconductor_openstack/openstack/__init__.py
nodeconductor_openstack/openstack/admin.py
nodeconductor_openstack/openstack/apps.py
nodeconductor_openstack/openstack/backend.py
nodeconductor_openstack/openstack/executors.py
nodeconductor_openstack/openstack/extension.py
nodeconductor_openstack/openstack/filters.py
nodeconductor_openstack/openstack/handlers.py
nodeconductor_openstack/openstack/log.py
nodeconductor_openstack/openstack/models.py
nodeconductor_openstack/openstack/serializers.py
nodeconductor_openstack/openstack/urls.py
nodeconductor_openstack/openstack/views.py
nodeconductor_openstack/openstack/management/__init__.py
nodeconductor_openstack/openstack/management/commands/__init__.py
nodeconductor_openstack/openstack/management/commands/initsecuritygroups.py
nodeconductor_openstack/openstack/migrations/0001_initial.py
nodeconductor_openstack/openstack/migrations/0002_volume.py
nodeconductor_openstack/openstack/migrations/0003_snapshot.py
nodeconductor_openstack/openstack/migrations/0004_dr_and_volume_backups.py
nodeconductor_openstack/openstack/migrations/0005_ipmapping.py
nodeconductor_openstack/openstack/migrations/0006_backups_restorations.py
nodeconductor_openstack/openstack/migrations/0007_add_instance_tenant.py
nodeconductor_openstack/openstack/migrations/0008_require_instance_tenant.py
nodeconductor_openstack/openstack/migrations/0009_add_security_group_tenant.py
nodeconductor_openstack/openstack/migrations/0010_require_security_group_tenant.py
nodeconductor_openstack/openstack/migrations/0011_add_floating_ip_tenant.py
nodeconductor_openstack/openstack/migrations/0012_require_floating_ip_tenant.py
nodeconductor_openstack/openstack/migrations/0013_add_dr_backups_to_schedule.py
nodeconductor_openstack/openstack/migrations/0014_instance_volumes.py
nodeconductor_openstack/openstack/migrations/0015_instance_runtime_state.py
nodeconductor_openstack-0.37.5.dist-info/DESCRIPTION.rst
nodeconductor_openstack-0.37.5.dist-info/METADATA
nodeconductor_openstack-0.37.5.dist-info/RECORD
nodeconductor_openstack-0.37.5.dist-info/WHEEL
nodeconductor_openstack-0.37.5.dist-info/entry_points.txt
nodeconductor_openstack-0.37.5.dist-info/metadata.json
nodeconductor_openstack-0.37.5.dist-info/top_level.txt
