Metadata-Version: 2.0
Name: nodeconductor-openstack
Version: 0.37.5
Summary: Waldur plugin for managing OpenStack resources.
Home-page: http://waldur.com
Author: OpenNode Team
Author-email: info@opennodecloud.com
License: MIT
Platform: UNKNOWN
Classifier: Framework :: Django
Classifier: Intended Audience :: Developers
Classifier: Intended Audience :: System Administrators
Classifier: Operating System :: OS Independent
Classifier: License :: OSI Approved :: MIT License
Requires-Dist: Babel (>=2.3.4,!=2.4.0)
Requires-Dist: iptools (>=0.6.1)
Requires-Dist: nodeconductor (>0.148.3)
Requires-Dist: pbr (!=2.1.0)
Requires-Dist: python-ceilometerclient (>=2.3.0)
Requires-Dist: python-cinderclient (>=1.6.0)
Requires-Dist: python-glanceclient (>=2.0.0)
Requires-Dist: python-keystoneclient (>=2.3.1)
Requires-Dist: python-neutronclient (>=4.1.1)
Requires-Dist: python-novaclient (>=3.3.0)
Provides-Extra: dev
Requires-Dist: Sphinx (==1.2.2); extra == 'dev'
Provides-Extra: tests
Requires-Dist: ddt (>=1.0.0); extra == 'tests'
